dqxbzr/__init__.py
dqxbzr/_core/__init__.py
dqxbzr/_core/_api.py
dqxbzr/_core/_data.py
dqxbzr/_core/_pages/__init__.py
dqxbzr/_core/_pages/_item_data.py
dqxbzr/_core/_pages/_item_search.py
dqxbzr/_core/_pages/_listing_search.py
dqxbzr/_core/_pages/_utils.py
dqxbzr/_core/_types.py
dqxbzr/playwright/__init__.py
dqxbzr/playwright/_page_fetcher.py
dqxbzr/py.typed
dqxbzr-0.1.0.dist-info/WHEEL
dqxbzr-0.1.0.dist-info/METADATA
dqxbzr-0.1.0.dist-info/RECORD
