Metadata-Version: 2.4
Name: dqxbzr
Version: 0.1.0
Summary: A utility library for scraping bazaar data from DQX Hiroba.
Author: Yepisan
Author-email: Yepisan <yepisan@fluffy.dev>
License-Expression: ISC
Classifier: Development Status :: 1 - Planning
Classifier: Intended Audience :: Developers
Classifier: License :: OSI Approved :: ISC License (ISCL)
Classifier: Operating System :: OS Independent
Classifier: Programming Language :: Python :: 3
Classifier: Programming Language :: Python :: 3.12
Classifier: Programming Language :: Python :: 3.13
Classifier: Topic :: Software Development :: Libraries :: Python Modules
Classifier: Typing :: Typed
Requires-Dist: lxml>=5.4.0
Requires-Dist: playwright>=1.52.0 ; extra == 'playwright'
Requires-Python: >=3.12
Project-URL: issues, https://github.com/yepisan/dqxbzr/issues
Project-URL: source, https://github.com/yepisan/dqxbzr
Provides-Extra: playwright
